census_cb/__init__.py
census_cb/census_cb.py
census_cb-0.1.0.dist-info/LICENSE
census_cb-0.1.0.dist-info/METADATA
census_cb-0.1.0.dist-info/WHEEL
census_cb-0.1.0.dist-info/top_level.txt
census_cb-0.1.0.dist-info/RECORD
