Metadata-Version: 2.1
Name: census-cb
Version: 0.1.0
Summary: Wrapper for downloading and processing Cartography Boundaries from the US Census Bureau
Home-page: https://github.com/tcramm0nd/census-cb
Author: Tim Crammond
Author-email: author@example.com
License: UNKNOWN
Project-URL: Bug Tracker, https://github.com/tcramm0nd/census-cb/issues
Platform: UNKNOWN
Classifier: Programming Language :: Python :: 3
Classifier: License :: OSI Approved :: MIT License
Classifier: Operating System :: OS Independent
Requires-Python: >=3.6
License-File: LICENSE
Requires-Dist: geopandas (==0.9.0)
Requires-Dist: pandas (==1.3.2)
Requires-Dist: requests (==2.26.0)
